{
	"sigma":[
		"a",
		"b",
		"c",
		"d",
		"e"
	],
	"init":"1",
	"name":"8_5_3-3",
	"l":[
		"1",
		"2",
		"3",
		"4",
		"5",
		"6",
		"7",
		"8"
	],
	"tran":{
		"22":[
			"5",
			"c",
			"[0,3)",
			"r",
			"7"
		],
		"23":[
			"5",
			"d",
			"(7,26)",
			"r",
			"5"
		],
		"24":[
			"5",
			"e",
			"(16,21)",
			"n",
			"1"
		],
		"25":[
			"6",
			"a",
			"[12,13)",
			"r",
			"8"
		],
		"26":[
			"6",
			"b",
			"(15,27)",
			"n",
			"6"
		],
		"27":[
			"6",
			"c",
			"[19,24]",
			"r",
			"1"
		],
		"28":[
			"6",
			"d",
			"(0,18)",
			"n",
			"8"
		],
		"29":[
			"6",
			"e",
			"[2,3]",
			"r",
			"4"
		],
		"30":[
			"7",
			"a",
			"[16,28]",
			"r",
			"7"
		],
		"31":[
			"7",
			"b",
			"(16,26]",
			"r",
			"5"
		],
		"10":[
			"3",
			"a",
			"[13,14]",
			"r",
			"8"
		],
		"32":[
			"7",
			"c",
			"(5,22]",
			"r",
			"3"
		],
		"11":[
			"3",
			"b",
			"[18,26]",
			"r",
			"1"
		],
		"33":[
			"7",
			"d",
			"[4,14)",
			"n",
			"4"
		],
		"12":[
			"3",
			"c",
			"[1,2)",
			"r",
			"4"
		],
		"34":[
			"7",
			"e",
			"[5,13)",
			"r",
			"5"
		],
		"13":[
			"3",
			"d",
			"(3,21)",
			"r",
			"4"
		],
		"35":[
			"8",
			"a",
			"[8,11]",
			"r",
			"6"
		],
		"14":[
			"3",
			"e",
			"(0,7)",
			"r",
			"3"
		],
		"36":[
			"8",
			"b",
			"[9,11]",
			"r",
			"4"
		],
		"15":[
			"4",
			"a",
			"[4,21]",
			"r",
			"1"
		],
		"37":[
			"8",
			"c",
			"[7,11)",
			"r",
			"2"
		],
		"16":[
			"4",
			"b",
			"(23,26]",
			"r",
			"7"
		],
		"38":[
			"8",
			"d",
			"[27,28]",
			"r",
			"1"
		],
		"17":[
			"4",
			"c",
			"[17,28]",
			"r",
			"2"
		],
		"39":[
			"8",
			"e",
			"(6,14]",
			"r",
			"8"
		],
		"18":[
			"4",
			"d",
			"[14,16)",
			"n",
			"8"
		],
		"19":[
			"4",
			"e",
			"[15,21)",
			"r",
			"8"
		],
		"0":[
			"1",
			"a",
			"(7,17]",
			"r",
			"8"
		],
		"1":[
			"1",
			"b",
			"[7,13]",
			"r",
			"8"
		],
		"2":[
			"1",
			"c",
			"[23,26)",
			"r",
			"8"
		],
		"3":[
			"1",
			"d",
			"[7,15)",
			"r",
			"6"
		],
		"4":[
			"1",
			"e",
			"(3,4)",
			"r",
			"4"
		],
		"5":[
			"2",
			"a",
			"(12,28]",
			"r",
			"1"
		],
		"6":[
			"2",
			"b",
			"(11,17]",
			"r",
			"8"
		],
		"7":[
			"2",
			"c",
			"(25,28)",
			"r",
			"5"
		],
		"8":[
			"2",
			"d",
			"(17,19)",
			"r",
			"8"
		],
		"9":[
			"2",
			"e",
			"[8,10)",
			"r",
			"6"
		],
		"20":[
			"5",
			"a",
			"[4,7)",
			"r",
			"4"
		],
		"21":[
			"5",
			"b",
			"(6,17]",
			"r",
			"1"
		]
	},
	"accept":[
		"8"
	]
}